{
    "weekly_2026-05-11": [
        {
            "user_id": "660209948877127701",
            "score": 20240.5,
            "v": 10075.25,
            "t": 90.0
        },
        {
            "user_id": "885760321938132992",
            "score": 14699.0,
            "v": 7292.0,
            "t": 115.0
        },
        {
            "user_id": "1345907948647354492",
            "score": 13219.0,
            "v": 6467.0,
            "t": 285.0
        },
        {
            "user_id": "1170482208994238614",
            "score": 891.0,
            "v": 444.0,
            "t": 3.0
        },
        {
            "user_id": "661924032870088705",
            "score": 704.0,
            "v": 348.0,
            "t": 8.0
        },
        {
            "user_id": "1498428531573653656",
            "score": 399.0,
            "v": 199.0,
            "t": 1.0
        },
        {
            "user_id": "1344757429660815525",
            "score": 21.0,
            "v": 10.0,
            "t": 1.0
        },
        {
            "user_id": "1351510603415420989",
            "score": 10.0,
            "v": 5.0,
            "t": 0
        },
        {
            "user_id": "1461315192578113627",
            "score": 4.0,
            "v": 2.0,
            "t": 0
        },
        {
            "user_id": "941663107653181510",
            "score": 1.0,
            "v": 0,
            "t": 1.0
        }
    ]
}